{"name":"can-symlink","version":"1.0.0","directDependencies":1,"dependencies":2,"distinctDependencies":2,"description":"Utility module to determine if fs.symlink commands will succeed. Useful for win32 enviornments where special permission is required for symlinking.","tree":{"data":[["can-symlink@1.0.0",{"name":"can-symlink","version":"1.0.0","count":2}],["tmp@0.0.28",{"name":"tmp","version":"0.0.28","count":1}],["os-tmpdir@1.0.2",{"name":"os-tmpdir","version":"1.0.2","count":0}]],"tree":{"id":"can-symlink@1.0.0","dependencies":[{"id":"tmp@0.0.28","dependencies":[{"id":"os-tmpdir@1.0.2"}]}]}}}