{"name":"collection-map","version":"1.0.0","directDependencies":3,"dependencies":7,"distinctDependencies":5,"description":"Returns an array of mapped values from an array or object.","dependencyTree":{"name":"collection-map","version":"1.0.0","transitiveCount":7,"loop":false,"dependencies":[{"name":"arr-map","version":"2.0.2","transitiveCount":2,"loop":false,"dependencies":[{"name":"make-iterator","version":"1.0.1","transitiveCount":1,"loop":false,"dependencies":[{"name":"kind-of","version":"6.0.3","transitiveCount":0,"loop":false,"dependencies":[]}]}]},{"name":"for-own","version":"1.0.0","transitiveCount":1,"loop":false,"dependencies":[{"name":"for-in","version":"1.0.2","transitiveCount":0,"loop":false,"dependencies":[]}]},{"name":"make-iterator","version":"1.0.1","transitiveCount":1,"loop":false,"dependencies":[{"name":"kind-of","version":"6.0.3","transitiveCount":0,"loop":false,"dependencies":[]}]}]}}