{"name":"eventsource","version":"1.0.7","directDependencies":1,"dependencies":4,"distinctDependencies":4,"description":"W3C compliant EventSource client for Node.js and browser (polyfill)","tree":{"data":[{"id":0,"name":"eventsource","version":"1.0.7","count":4},{"id":1,"name":"original","version":"1.0.2","count":3},{"id":2,"name":"url-parse","version":"1.4.7","count":2},{"id":3,"name":"querystringify","version":"2.1.1","count":0},{"id":4,"name":"requires-port","version":"1.0.0","count":0}],"tree":{"id":0,"dependencies":[{"id":1,"dependencies":[{"id":2,"dependencies":[{"id":3},{"id":4}]}]}]}}}