{"name":"html-encoding-sniffer","version":"2.0.1","directDependencies":1,"dependencies":3,"distinctDependencies":3,"description":"Sniff the encoding from a HTML byte stream","tree":{"data":[{"id":0,"name":"html-encoding-sniffer","version":"2.0.1","count":3},{"id":1,"name":"whatwg-encoding","version":"1.0.5","count":2},{"id":2,"name":"iconv-lite","version":"0.4.24","count":1},{"id":3,"name":"safer-buffer","version":"2.1.2","count":0}],"tree":{"id":0,"dependencies":[{"id":1,"dependencies":[{"id":2,"dependencies":[{"id":3}]}]}]}}}