{"name":"import-fresh","version":"3.2.1","directDependencies":2,"dependencies":3,"distinctDependencies":3,"description":"Import a module while bypassing the cache","dependencyTree":{"name":"import-fresh","version":"3.2.1","transitiveCount":3,"loop":false,"dependencies":[{"name":"parent-module","version":"1.0.1","transitiveCount":1,"loop":false,"dependencies":[{"name":"callsites","version":"3.1.0","transitiveCount":0,"loop":false,"dependencies":[]}]},{"name":"resolve-from","version":"4.0.0","transitiveCount":0,"loop":false,"dependencies":[]}]}}